{
  "profile_img": "https://fmdataba.com/images/p/80562.png",
  "name": "Apostolos Giannou",
  "birth_date": "25/1/1990",
  "nation": "Australia AUS",
  "position": "AM (C), ST (C)",
  "foot": "Right",
  "korean": "아 포 스 톨 로 스 지 안 누",
  "abilities": {
    "technical": {
      "Corners": 7,
      "Crossing": 10,
      "Dribbling": 13,
      "Finishing": 13,
      "First Touch": 14,
      "Free Kick": 8,
      "Heading": 12,
      "Long Shots": 10,
      "Long Throws": 4,
      "Marking": 9,
      "Passing": 13,
      "Penalty Taking": 12,
      "Tackling": 10,
      "Technique": 14
    },
    "mental": {
      "Aggression": 8,
      "Anticipation": 13,
      "Bravery": 9,
      "Composure": 12,
      "Concentration": 12,
      "Decisions": 13,
      "Determination": 10,
      "Flair": 15,
      "Leadership": 8,
      "Off The Ball": 13,
      "Positioning": 8,
      "Teamwork": 13,
      "Vision": 14,
      "Work Rate": 12
    },
    "physical": {
      "Acceleration": 12,
      "Agility": 12,
      "Balance": 13,
      "Jumping Reach": 13,
      "Natural Fitness": 13,
      "Pace": 13,
      "Stamina": 13,
      "Strength": 12
    }
  }
}