{
  "profile_img": "https://fmdataba.com/images/p/46371.png",
  "name": "Dylan McGowan",
  "birth_date": "6/8/1991",
  "nation": "Australia AUS",
  "position": "D (RC), DM",
  "foot": "Right",
  "korean": "딜 런 맥 고 완",
  "abilities": {
    "technical": {
      "Corners": 5,
      "Crossing": 6,
      "Dribbling": 7,
      "Finishing": 6,
      "First Touch": 8,
      "Free Kick": 7,
      "Heading": 14,
      "Long Shots": 7,
      "Long Throws": 8,
      "Marking": 12,
      "Passing": 8,
      "Penalty Taking": 10,
      "Tackling": 13,
      "Technique": 8
    },
    "mental": {
      "Aggression": 12,
      "Anticipation": 10,
      "Bravery": 14,
      "Composure": 8,
      "Concentration": 12,
      "Decisions": 10,
      "Determination": 12,
      "Flair": 5,
      "Leadership": 10,
      "Off The Ball": 8,
      "Positioning": 13,
      "Teamwork": 14,
      "Vision": 8,
      "Work Rate": 14
    },
    "physical": {
      "Acceleration": 12,
      "Agility": 11,
      "Balance": 14,
      "Jumping Reach": 13,
      "Natural Fitness": 14,
      "Pace": 12,
      "Stamina": 13,
      "Strength": 13
    }
  }
}