{
  "profile_img": "https://fmdataba.com/images/p/46507.png",
  "name": "Kwon Soon-Hyung",
  "birth_date": "16/6/1986",
  "nation": "South Korea KOR",
  "position": "DM, M (C)",
  "foot": "Right",
  "korean": "권 순 형",
  "abilities": {
    "technical": {
      "Corners": 11,
      "Crossing": 11,
      "Dribbling": 11,
      "Finishing": 9,
      "First Touch": 12,
      "Free Kick": 12,
      "Heading": 7,
      "Long Shots": 11,
      "Long Throws": 4,
      "Marking": 9,
      "Passing": 13,
      "Penalty Taking": 12,
      "Tackling": 10,
      "Technique": 13
    },
    "mental": {
      "Aggression": 9,
      "Anticipation": 11,
      "Bravery": 9,
      "Composure": 12,
      "Concentration": 9,
      "Decisions": 11,
      "Determination": 10,
      "Flair": 14,
      "Leadership": 8,
      "Off The Ball": 12,
      "Positioning": 10,
      "Teamwork": 12,
      "Vision": 15,
      "Work Rate": 12
    },
    "physical": {
      "Acceleration": 11,
      "Agility": 13,
      "Balance": 9,
      "Jumping Reach": 5,
      "Natural Fitness": 12,
      "Pace": 12,
      "Stamina": 11,
      "Strength": 10
    }
  }
}