{
  "profile_img": "https://fmdataba.com/images/p/61486.png",
  "name": "Jonathan Bamba",
  "birth_date": "26/3/1996",
  "nation": "France",
  "position": "AM (RL), ST (C)",
  "foot": "Right",
  "korean": "조 선 밤 바",
  "abilities": {
    "technical": {
      "Corners": 11,
      "Crossing": 12,
      "Dribbling": 15,
      "Finishing": 13,
      "First Touch": 12,
      "Free Kick": 8,
      "Heading": 5,
      "Long Shots": 12,
      "Long Throws": 7,
      "Marking": 4,
      "Passing": 11,
      "Penalty Taking": 10,
      "Tackling": 4,
      "Technique": 13
    },
    "mental": {
      "Aggression": 12,
      "Anticipation": 12,
      "Bravery": 11,
      "Composure": 13,
      "Concentration": 11,
      "Decisions": 10,
      "Determination": 10,
      "Flair": 11,
      "Leadership": 7,
      "Off The Ball": 14,
      "Positioning": 7,
      "Teamwork": 9,
      "Vision": 10,
      "Work Rate": 12
    },
    "physical": {
      "Acceleration": 16,
      "Agility": 14,
      "Balance": 14,
      "Jumping Reach": 6,
      "Natural Fitness": 14,
      "Pace": 15,
      "Stamina": 14,
      "Strength": 13
    }
  }
}