{
  "profile_img": "https://fmdataba.com/images/p/6787.png",
  "name": "Luca Plogmann",
  "birth_date": "10/3/2000",
  "nation": "Germany",
  "position": "GK",
  "foot": "Left",
  "korean": "루 카 플 레 그 만",
  "abilities": {
    "technical": {
      "Aerial Reach": 11,
      "Communication": 14,
      "Eccentricity": 15,
      "First Touch": 11,
      "Handling": 9,
      "Kicking": 10,
      "Passing": 12,
      "Reflexes": 13,
      "Rushing Out": 15,
      "Throwing": 11
    },
    "mental": {
      "Aggression": 10,
      "Anticipation": 11,
      "Bravery": 11,
      "Composure": 16,
      "Concentration": 9,
      "Decisions": 12,
      "Determination": 16,
      "Flair": 2,
      "Leadership": 11,
      "Off The Ball": 2,
      "Positioning": 9,
      "Teamwork": 15,
      "Vision": 8,
      "Work Rate": 12
    },
    "physical": {
      "Acceleration": 11,
      "Agility": 12,
      "Balance": 10,
      "Jumping Reach": 13,
      "Natural Fitness": 13,
      "Pace": 10,
      "Stamina": 9,
      "Strength": 10
    }
  }
}