{
  "profile_img": "https://fmdataba.com/images/p/26026.png",
  "name": "Mathias Pereira Lage",
  "birth_date": "30/11/1996",
  "nation": "Portugal",
  "position": "M (C), AM (LC)",
  "foot": "Right Only",
  "korean": "마 티 아 스 페 레 이 라 라 지",
  "abilities": {
    "technical": {
      "Corners": 10,
      "Crossing": 12,
      "Dribbling": 11,
      "Finishing": 13,
      "First Touch": 13,
      "Free Kick": 14,
      "Heading": 11,
      "Long Shots": 16,
      "Long Throws": 8,
      "Marking": 8,
      "Passing": 13,
      "Penalty Taking": 12,
      "Tackling": 8,
      "Technique": 13
    },
    "mental": {
      "Aggression": 10,
      "Anticipation": 12,
      "Bravery": 8,
      "Composure": 12,
      "Concentration": 12,
      "Decisions": 12,
      "Determination": 14,
      "Flair": 14,
      "Leadership": 10,
      "Off The Ball": 13,
      "Positioning": 10,
      "Teamwork": 13,
      "Vision": 12,
      "Work Rate": 12
    },
    "physical": {
      "Acceleration": 13,
      "Agility": 14,
      "Balance": 10,
      "Jumping Reach": 11,
      "Natural Fitness": 13,
      "Pace": 12,
      "Stamina": 13,
      "Strength": 10
    }
  }
}