{
  "profile_img": "https://fmdataba.com/images/p/8660.png",
  "name": "Stijn Wuytens",
  "birth_date": "8/10/1989",
  "nation": "Belgium",
  "position": "D (C), DM, M (LC)",
  "foot": "Left Only",
  "korean": "스 틴 위 텐 스",
  "abilities": {
    "technical": {
      "Corners": 12,
      "Crossing": 10,
      "Dribbling": 10,
      "Finishing": 7,
      "First Touch": 12,
      "Free Kick": 14,
      "Heading": 12,
      "Long Shots": 13,
      "Long Throws": 8,
      "Marking": 13,
      "Passing": 13,
      "Penalty Taking": 10,
      "Tackling": 13,
      "Technique": 12
    },
    "mental": {
      "Aggression": 11,
      "Anticipation": 13,
      "Bravery": 12,
      "Composure": 12,
      "Concentration": 13,
      "Decisions": 12,
      "Determination": 14,
      "Flair": 13,
      "Leadership": 14,
      "Off The Ball": 14,
      "Positioning": 12,
      "Teamwork": 14,
      "Vision": 13,
      "Work Rate": 14
    },
    "physical": {
      "Acceleration": 11,
      "Agility": 12,
      "Balance": 13,
      "Jumping Reach": 12,
      "Natural Fitness": 15,
      "Pace": 11,
      "Stamina": 14,
      "Strength": 12
    }
  }
}